volkeno_paydunya_gateway_py/__init__.py
volkeno_paydunya_gateway_py/job.py
volkeno_paydunya_gateway_py-1.0.0.dist-info/LICENCE
volkeno_paydunya_gateway_py-1.0.0.dist-info/METADATA
volkeno_paydunya_gateway_py-1.0.0.dist-info/WHEEL
volkeno_paydunya_gateway_py-1.0.0.dist-info/top_level.txt
volkeno_paydunya_gateway_py-1.0.0.dist-info/RECORD
