Metadata-Version: 2.1
Name: volkeno-paydunya-gateway-py
Version: 1.0.0
Summary: Volkeno Paydunya Gateway Py is a module to integrate paydunya quickly in your backend
Home-page: https://github.com/VolkenoMakers/volkeno_paydunya_gateway_py
Author: VOLKENO
Author-email: contact@volkeno-tank.com
License: MIT
Keywords: core package
Classifier: Development Status :: 5 - Production/Stable
Classifier: License :: OSI Approved :: MIT License
Classifier: Programming Language :: Python :: 3
Classifier: Operating System :: OS Independent
Classifier: Intended Audience :: Developers
License-File: LICENCE
Requires-Dist: volkeno-paydunya-gateway-py
